[
  {
    "hreflang": "ar-AE",
    "href": "https://www.tumi.ae/ar/collections/golf-collection"
  },
  {
    "hreflang": "ar-KW",
    "href": "https://www.tumi.com.kw/ar/collections/golf-collection"
  },
  {
    "hreflang": "ar-SA",
    "href": "https://www.tumi.sa/ar/collections/golf-collection"
  },
  { "hreflang": "de-AT", "href": "https://at.tumi.com/taschen/tumi-sport/" },
  { "hreflang": "de-CH", "href": "https://ch.tumi.com/taschen/tumi-sport/" },
  { "hreflang": "de-DE", "href": "https://de.tumi.com/taschen/tumi-sport/" },
  { "hreflang": "de-LU", "href": "https://lu.tumi.com/de/taschen/tumi-sport/" },
  {
    "hreflang": "en-AE",
    "href": "https://www.tumi.ae/collections/golf-collection"
  },
  { "hreflang": "en-AT", "href": "https://at.tumi.com/en/bags/tumi-sport/" },
  { "hreflang": "en-AU", "href": "https://www.tumi.com.au/bags/tumi-sport/" },
  { "hreflang": "en-BE", "href": "https://be.tumi.com/en/bags/tumi-sport/" },
  { "hreflang": "en-ca", "href": "https://ca.tumi.com/en/c/bags/tumi-sport/" },
  { "hreflang": "en-CH", "href": "https://ch.tumi.com/en/bags/tumi-sport/" },
  { "hreflang": "en-CZ", "href": "https://cz.tumi.com/en/bags/tumi-sport/" },
  { "hreflang": "en-DE", "href": "https://de.tumi.com/en/bags/tumi-sport/" },
  { "hreflang": "en-DK", "href": "https://dk.tumi.com/en/bags/tumi-sport/" },
  { "hreflang": "en-ES", "href": "https://es.tumi.com/en/bags/tumi-sport/" },
  { "hreflang": "en-FI", "href": "https://fi.tumi.com/en/bags/tumi-sport/" },
  { "hreflang": "en-FR", "href": "https://fr.tumi.com/en/bags/tumi-sport/" },
  { "hreflang": "en-GB", "href": "https://uk.tumi.com/bags/tumi-sport/" },
  {
    "hreflang": "en-HK",
    "href": "https://www.tumi-hk.com/en/bags/shop-by-type/active-bags/"
  },
  { "hreflang": "en-HU", "href": "https://hu.tumi.com/en/bags/tumi-sport/" },
  {
    "hreflang": "en-ID",
    "href": "https://www.tumi.co.id/en/bags/shop-by-type/tumi-sport/"
  },
  { "hreflang": "en-IE", "href": "https://ie.tumi.com/bags/tumi-sport/" },
  {
    "hreflang": "en-IN",
    "href": "https://tumi.in/collections/collection-golfbags/"
  },
  { "hreflang": "en-IT", "href": "https://it.tumi.com/en/bags/tumi-sport/" },
  {
    "hreflang": "en-KW",
    "href": "https://www.tumi.com.kw/collections/golf-collection"
  },
  { "hreflang": "en-LU", "href": "https://lu.tumi.com/en/bags/tumi-sport/" },
  {
    "hreflang": "en-MO",
    "href": "https://www.tumi-hk.com/en/bags/shop-by-type/active-bags/"
  },
  {
    "hreflang": "en-MY",
    "href": "https://www.tumi.my/bags/shop-by-type/tumi-sports/"
  },
  { "hreflang": "en-NL", "href": "https://nl.tumi.com/en/bags/tumi-sport/" },
  { "hreflang": "en-NO", "href": "https://no.tumi.com/en/bags/tumi-sport/" },
  {
    "hreflang": "en-PH",
    "href": "https://www.tumi.ph/bag/bag-type/bag-type-active/"
  },
  { "hreflang": "en-PL", "href": "https://pl.tumi.com/en/bags/tumi-sport/" },
  {
    "hreflang": "en-SA",
    "href": "https://www.tumi.sa/collections/golf-collection"
  },
  { "hreflang": "en-SE", "href": "https://se.tumi.com/en/bags/tumi-sport/" },
  { "hreflang": "en-SG", "href": "https://www.tumi.sg/bags/tumi-sport/" },
  { "hreflang": "en-SK", "href": "https://sk.tumi.com/en/bags/tumi-sport/" },
  { "hreflang": "en-TH", "href": "https://www.tumi.co.th/en/bags/tumi-sport/" },
  { "hreflang": "en-us", "href": "https://www.tumi.com/c/bags/tumi-sport/" },
  { "hreflang": "es-cl", "href": "X" },
  { "hreflang": "es-ES", "href": "https://es.tumi.com/bolsas/tumi-sport/" },
  { "hreflang": "es-mx", "href": "X" },
  { "hreflang": "fr-BE", "href": "https://be.tumi.com/fr/sacs/tumi-sport/" },
  { "hreflang": "fr-ca", "href": "https://ca.tumi.com/fr/c/bags/tumi-sport/" },
  { "hreflang": "fr-CH", "href": "https://ch.tumi.com/fr/sacs/tumi-sport/" },
  { "hreflang": "fr-FR", "href": "https://fr.tumi.com/sacs/tumi-sport/" },
  { "hreflang": "fr-LU", "href": "https://lu.tumi.com/sacs/tumi-sport/" },
  {
    "hreflang": "id-ID",
    "href": "https://www.tumi.co.id/id/bags/shop-by-type/tumi-sport/"
  },
  { "hreflang": "it-CH", "href": "https://ch.tumi.com/it/borse/tumi-sport/" },
  { "hreflang": "it-IT", "href": "https://it.tumi.com/borse/tumi-sport/" },
  { "hreflang": "ja-JP", "href": "https://www.tumi.co.jp/bag/sports/" },
  {
    "hreflang": "ko-KR",
    "href": "https://www.tumi.co.kr/bag/bag-type/bag-type-active/"
  },
  { "hreflang": "nl-BE", "href": "https://be.tumi.com/tassen/tumi-sport/" },
  { "hreflang": "nl-NL", "href": "https://nl.tumi.com/tassen/tumi-sport/" },
  { "hreflang": "pl-PL", "href": "https://pl.tumi.com/torby/tumi-sport/" },
  {
    "hreflang": "pt-br",
    "href": "https://tumibrasil.com/collections/tumi-esporte"
  },
  { "hreflang": "pt-pt", "href": "https://www.tumi.pt/tumi-sport-golf_3" },
  {
    "hreflang": "th-TH",
    "href": "https://www.tumi.co.th/th/bags/mens/active-bags/"
  }
]
